odoo/addons/fetchmail_incoming_log/README.rst
odoo/addons/fetchmail_incoming_log/__init__.py
odoo/addons/fetchmail_incoming_log/__manifest__.py
odoo/addons/fetchmail_incoming_log/i18n/ca.po
odoo/addons/fetchmail_incoming_log/i18n/de.po
odoo/addons/fetchmail_incoming_log/i18n/es.po
odoo/addons/fetchmail_incoming_log/i18n/es_AR.po
odoo/addons/fetchmail_incoming_log/i18n/fetchmail_incoming_log.pot
odoo/addons/fetchmail_incoming_log/i18n/fr.po
odoo/addons/fetchmail_incoming_log/i18n/it.po
odoo/addons/fetchmail_incoming_log/i18n/pt_BR.po
odoo/addons/fetchmail_incoming_log/i18n/pt_PT.po
odoo/addons/fetchmail_incoming_log/i18n/sl.po
odoo/addons/fetchmail_incoming_log/i18n/tr.po
odoo/addons/fetchmail_incoming_log/models/__init__.py
odoo/addons/fetchmail_incoming_log/models/mail_thread.py
odoo/addons/fetchmail_incoming_log/readme/CONFIGURE.rst
odoo/addons/fetchmail_incoming_log/readme/CONTRIBUTORS.rst
odoo/addons/fetchmail_incoming_log/readme/DESCRIPTION.rst
odoo/addons/fetchmail_incoming_log/static/description/icon.png
odoo/addons/fetchmail_incoming_log/static/description/index.html
odoo_addon_fetchmail_incoming_log-15.0.1.0.0.12.dist-info/METADATA
odoo_addon_fetchmail_incoming_log-15.0.1.0.0.12.dist-info/WHEEL
odoo_addon_fetchmail_incoming_log-15.0.1.0.0.12.dist-info/top_level.txt
odoo_addon_fetchmail_incoming_log-15.0.1.0.0.12.dist-info/RECORD
